COPYING
MANIFEST.in
setup.py
Vanda.egg-info/PKG-INFO
Vanda.egg-info/SOURCES.txt
Vanda.egg-info/dependency_links.txt
Vanda.egg-info/requires.txt
Vanda.egg-info/top_level.txt
vanda/__init__.py
vanda/__init__.pyc
vanda/__pycache__/__init__.cpython-33.pyc
vanda/apps/__init__.py
vanda/apps/__init__.pyc
vanda/apps/__pycache__/__init__.cpython-33.pyc
vanda/apps/contactus/__init__.py
vanda/apps/contactus/forms.py
vanda/apps/contactus/models.py
vanda/apps/contactus/tests.py
vanda/apps/contactus/urls.py
vanda/apps/contactus/views.py
vanda/apps/contactus/locale/fa/LC_MESSAGES/django.po
vanda/apps/contactus/templates/contact_us.html
vanda/apps/dashboard/.gitignore
vanda/apps/dashboard/__init__.py
vanda/apps/dashboard/__init__.pyc
vanda/apps/dashboard/base.py
vanda/apps/dashboard/base.pyc
vanda/apps/dashboard/context_processors.py
vanda/apps/dashboard/context_processors.pyc
vanda/apps/dashboard/models.py
vanda/apps/dashboard/models.pyc
vanda/apps/dashboard/urls_temp.py
vanda/apps/dashboard/blocks/__init__.py
vanda/apps/dashboard/blocks/__init__.pyc
vanda/apps/dashboard/blocks/areas.py
vanda/apps/dashboard/blocks/areas.pyc
vanda/apps/dashboard/blocks/bars.py
vanda/apps/dashboard/blocks/bars.pyc
vanda/apps/dashboard/blocks/base.py
vanda/apps/dashboard/blocks/base.pyc
vanda/apps/dashboard/blocks/slide.py
vanda/apps/dashboard/blocks/slide.pyc
vanda/apps/dashboard/statics/css/blocks/body.css
vanda/apps/dashboard/statics/css/blocks/config.css
vanda/apps/dashboard/statics/css/blocks/header.css
vanda/apps/dashboard/statics/css/widgets/setting_button.css
vanda/apps/dashboard/statics/css/widgets/ultra_blog_widget.css
vanda/apps/dashboard/statics/css/widgets/user_button.css
vanda/apps/dashboard/statics/js/blocks/horizontalbar.js
vanda/apps/dashboard/statics/js/blocks/slidearea.js
vanda/apps/dashboard/statics/js/blocks/widgetarea.js
vanda/apps/dashboard/statics/js/widgets/addwidgetbutton.js
vanda/apps/dashboard/statics/js/widgets/settingbutton.js
vanda/apps/dashboard/statics/js/widgets/ultrablog.js
vanda/apps/dashboard/statics/js/widgets/userbutton.js
vanda/apps/dashboard/templates/dashboard/base.html
