Metadata-Version: 1.1
Name: Vanda
Version: 2.1.11
Summary: Rapid web development platform based on Django framework
Home-page: http://vanda.yellowen.com/
Author: Sameer Rahmani
Author-email: lxsameer@gnu.org
License: GPL v3
Download-URL: http://vanda.yellowen.com/downloads/
Keywords: web development framework platform
Platform: UNKNOWN
Classifier: Development Status :: 5 - Production/Stable
Classifier: Environment :: Console
Classifier: Intended Audience :: Developers
Classifier: License :: OSI Approved :: GNU General Public License (GPL)
Classifier: Operating System :: POSIX :: Linux
Classifier: Programming Language :: Python
Classifier: Topic :: Software Development :: Libraries :: Python Modules
Classifier: Topic :: Utilities
